[{"chaos_penalty":0,"conflict_penalty":0,"contention":{"contention_points":0,"contention_probability":0,"contention_score":0,"contention_type":"none"},"cross_function":{"called_funcs_count":0,"caller_funcs_count":1,"cross_func_score":5,"external_func_propagation":false,"hot_func_usage":false},"data_flow":{"avg_uses_per_phase":0,"data_flow_score":15,"has_dormant_phase":true,"has_init_phase":false,"has_read_only_phase":true},"dynamic_hot_static_low":false,"forced_hot":false,"location":"multidimensional_array:<no_dbg>","loop_depth":2,"may_conflict":false,"parallel":false,"parallel_score":0,"score":189.66590320625505,"size":400,"ssa_penalty":1,"static_hot_dynamic_cold":false,"stream":false,"stream_score":10.479535488828244,"thread_partitioned":false,"trip_count":1,"vector_score":0,"vectorized":false},{"chaos_penalty":0,"conflict_penalty":0,"contention":{"contention_points":0,"contention_probability":0,"contention_score":0,"contention_type":"none"},"cross_function":{"called_funcs_count":0,"caller_funcs_count":0,"cross_func_score":5,"external_func_propagation":false,"hot_func_usage":false},"data_flow":{"avg_uses_per_phase":0,"data_flow_score":15,"has_dormant_phase":true,"has_init_phase":false,"has_read_only_phase":true},"dynamic_hot_static_low":false,"forced_hot":false,"location":"main:<no_dbg>","loop_depth":1,"may_conflict":false,"parallel":false,"parallel_score":0,"score":148.95890753662241,"size":4000,"ssa_penalty":0.5,"static_hot_dynamic_cold":false,"stream":false,"stream_score":4.9974634448255379,"thread_partitioned":false,"trip_count":1,"vector_score":0,"vectorized":false},{"chaos_penalty":0,"conflict_penalty":0,"contention":{"contention_points":0,"contention_probability":0,"contention_score":0,"contention_type":"none"},"cross_function":{"called_funcs_count":0,"caller_funcs_count":1,"cross_func_score":5,"external_func_propagation":false,"hot_func_usage":false},"data_flow":{"avg_uses_per_phase":0,"data_flow_score":15,"has_dormant_phase":true,"has_init_phase":false,"has_read_only_phase":true},"dynamic_hot_static_low":false,"forced_hot":false,"location":"multidimensional_array:<no_dbg>","loop_depth":1,"may_conflict":false,"parallel":false,"parallel_score":0,"score":133.24975226318492,"size":800,"ssa_penalty":1,"static_hot_dynamic_cold":false,"stream":false,"stream_score":4.9974634448255379,"thread_partitioned":false,"trip_count":1,"vector_score":0,"vectorized":false},{"chaos_penalty":0,"conflict_penalty":0,"contention":{"contention_points":0,"contention_probability":0,"contention_score":0,"contention_type":"none"},"cross_function":{"called_funcs_count":0,"caller_funcs_count":0,"cross_func_score":5,"external_func_propagation":false,"hot_func_usage":false},"data_flow":{"avg_uses_per_phase":0,"data_flow_score":15,"has_dormant_phase":true,"has_init_phase":false,"has_read_only_phase":true},"dynamic_hot_static_low":false,"forced_hot":false,"location":"main:<no_dbg>","loop_depth":0,"may_conflict":false,"parallel":false,"parallel_score":0,"score":38.017483321057682,"size":40000000,"ssa_penalty":0,"static_hot_dynamic_cold":false,"stream":false,"stream_score":0,"thread_partitioned":false,"trip_count":1,"vector_score":0,"vectorized":false},{"chaos_penalty":0,"conflict_penalty":0,"contention":{"contention_points":0,"contention_probability":0,"contention_score":0,"contention_type":"none"},"cross_function":{"called_funcs_count":0,"caller_funcs_count":1,"cross_func_score":5,"external_func_propagation":false,"hot_func_usage":false},"data_flow":{"avg_uses_per_phase":0,"data_flow_score":15,"has_dormant_phase":true,"has_init_phase":false,"has_read_only_phase":true},"dynamic_hot_static_low":false,"forced_hot":false,"location":"cross_function_memory:<no_dbg>","loop_depth":0,"may_conflict":false,"parallel":false,"parallel_score":0,"score":25.6573486328125,"size":4000000,"ssa_penalty":0,"static_hot_dynamic_cold":false,"stream":false,"stream_score":0,"thread_partitioned":false,"trip_count":1,"vector_score":0,"vectorized":false},{"chaos_penalty":0,"conflict_penalty":0,"contention":{"contention_points":0,"contention_probability":0,"contention_score":0,"contention_type":"none"},"cross_function":{"called_funcs_count":0,"caller_funcs_count":0,"cross_func_score":5,"external_func_propagation":false,"hot_func_usage":false},"data_flow":{"avg_uses_per_phase":0,"data_flow_score":15,"has_dormant_phase":true,"has_init_phase":false,"has_read_only_phase":true},"dynamic_hot_static_low":false,"forced_hot":false,"location":"main:<no_dbg>","loop_depth":0,"may_conflict":false,"parallel":false,"parallel_score":0,"score":19.27288818359375,"size":8000,"ssa_penalty":0,"static_hot_dynamic_cold":false,"stream":false,"stream_score":0,"thread_partitioned":false,"trip_count":1,"vector_score":0,"vectorized":false},{"chaos_penalty":0,"conflict_penalty":0,"contention":{"contention_points":0,"contention_probability":0,"contention_score":0,"contention_type":"none"},"cross_function":{"called_funcs_count":0,"caller_funcs_count":1,"cross_func_score":5,"external_func_propagation":false,"hot_func_usage":false},"data_flow":{"avg_uses_per_phase":0,"data_flow_score":15,"has_dormant_phase":true,"has_init_phase":false,"has_read_only_phase":true},"dynamic_hot_static_low":false,"forced_hot":false,"location":"multidimensional_array:<no_dbg>","loop_depth":0,"may_conflict":false,"parallel":false,"parallel_score":0,"score":19.252288818359375,"size":800,"ssa_penalty":0,"static_hot_dynamic_cold":false,"stream":false,"stream_score":0,"thread_partitioned":false,"trip_count":1,"vector_score":0,"vectorized":false},{"chaos_penalty":0,"conflict_penalty":0,"contention":{"contention_points":0,"contention_probability":0,"contention_score":0,"contention_type":"none"},"cross_function":{"called_funcs_count":0,"caller_funcs_count":0,"cross_func_score":5,"external_func_propagation":false,"hot_func_usage":false},"data_flow":{"avg_uses_per_phase":0,"data_flow_score":15,"has_dormant_phase":true,"has_init_phase":false,"has_read_only_phase":true},"dynamic_hot_static_low":false,"forced_hot":false,"location":"main:<no_dbg>","loop_depth":0,"may_conflict":false,"parallel":false,"parallel_score":0,"score":19.250114440917969,"size":40,"ssa_penalty":0,"static_hot_dynamic_cold":false,"stream":false,"stream_score":0,"thread_partitioned":false,"trip_count":1,"vector_score":0,"vectorized":false}]
